esa_cci_sm/__init__.py
esa_cci_sm/grid.py
esa_cci_sm/interface.py
esa_cci_sm/reshuffle.py
esa_cci_sm/metadata/esa_cci_sm_v03_ACTIVE.ini
esa_cci_sm/metadata/esa_cci_sm_v03_COMBINED.ini
esa_cci_sm/metadata/esa_cci_sm_v03_PASSIVE.ini
esa_cci_sm/metadata/esa_cci_sm_v04_ACTIVE.ini
esa_cci_sm/metadata/esa_cci_sm_v04_COMBINED.ini
esa_cci_sm/metadata/esa_cci_sm_v04_PASSIVE.ini
esa_cci_sm/metadata/esa_cci_sm_v05_ACTIVE.ini
esa_cci_sm/metadata/esa_cci_sm_v05_COMBINED.ini
esa_cci_sm/metadata/esa_cci_sm_v05_PASSIVE.ini
esa_cci_sm/metadata/esa_cci_sm_v06_ACTIVE.ini
esa_cci_sm/metadata/esa_cci_sm_v06_COMBINED.ini
esa_cci_sm/metadata/esa_cci_sm_v06_PASSIVE.ini
esa_cci_sm/metadata/esa_cci_sm_v07_ACTIVE.ini
esa_cci_sm/metadata/esa_cci_sm_v07_COMBINED.ini
esa_cci_sm/metadata/esa_cci_sm_v07_PASSIVE.ini
esa_cci_sm/metadata/esa_cci_sm_v08_ACTIVE.ini
esa_cci_sm/metadata/esa_cci_sm_v08_COMBINED.ini
esa_cci_sm/metadata/esa_cci_sm_v08_PASSIVE.ini
esa_cci_sm/metadata/esa_cci_sm_v09_ACTIVE.ini
esa_cci_sm/metadata/esa_cci_sm_v09_COMBINED.ini
esa_cci_sm/metadata/esa_cci_sm_v09_PASSIVE.ini
esa_cci_sm-0.5.0.dist-info/AUTHORS.rst
esa_cci_sm-0.5.0.dist-info/LICENSE.txt
esa_cci_sm-0.5.0.dist-info/METADATA
esa_cci_sm-0.5.0.dist-info/WHEEL
esa_cci_sm-0.5.0.dist-info/entry_points.txt
esa_cci_sm-0.5.0.dist-info/top_level.txt
esa_cci_sm-0.5.0.dist-info/RECORD
