Metadata-Version: 2.1
Name: esa_cci_sm
Version: 0.5.0
Summary: Reading and reshuffling of CCI soil moisture
Home-page: https://github.com/pyscaffold/pyscaffold/
Author: TU Wien
Author-email: remote.sensing@geo.tuwien.ac.at
License: mit
Project-URL: Documentation, https://pyscaffold.org/
Platform: any
Classifier: Development Status :: 4 - Beta
Classifier: Programming Language :: Python
Requires-Python: >=3.8
License-File: LICENSE.txt
License-File: AUTHORS.rst
Requires-Dist: numpy
Requires-Dist: pandas
Requires-Dist: pygeobase
Requires-Dist: pyresample
Requires-Dist: netCDF4
Requires-Dist: configparser
Requires-Dist: repurpose
Requires-Dist: pynetcf
Requires-Dist: parse
Requires-Dist: pygeogrids
Requires-Dist: smecv-grid>=0.3
Requires-Dist: more-itertools
Provides-Extra: docs
Requires-Dist: sphinx-rtd-theme; extra == "docs"
Provides-Extra: testing
Requires-Dist: pytest; extra == "testing"
Requires-Dist: pytest-cov; extra == "testing"
Requires-Dist: coverage; extra == "testing"
